quantum_dynamics/__init__.py
quantum_dynamics/tdse.py
quantum_dynamics/tise.py
quantum_dynamics/utils.py
quantum_dynamics/_krylov/__init__.py
quantum_dynamics/_krylov/_krylov_subspace.py
quantum_dynamics/_krylov/exponential.py
quantum_dynamics/_krylov/type_checking.py
quantum_dynamics/_krylov/tests/__init__.py
quantum_dynamics/_krylov/tests/test_expm_multiply_krylov.py
quantum_dynamics/_krylov/tests/test_krylov_subspace.py
quantum_dynamics/tests/__init__.py
quantum_dynamics/tests/test_tise.py
quantum_dynamics/tests/test_utils.py
quantum_dynamics-0.1.dev14.data/scripts/plot_time_evolution
quantum_dynamics-0.1.dev14.data/scripts/qdyn_laser
quantum_dynamics-0.1.dev14.dist-info/DESCRIPTION.rst
quantum_dynamics-0.1.dev14.dist-info/METADATA
quantum_dynamics-0.1.dev14.dist-info/RECORD
quantum_dynamics-0.1.dev14.dist-info/WHEEL
quantum_dynamics-0.1.dev14.dist-info/metadata.json
quantum_dynamics-0.1.dev14.dist-info/top_level.txt
quantum_dynamics-0.1.dev14.dist-info/zip-safe
