Metadata-Version: 2.0
Name: quantum-dynamics
Version: 0.1.dev14
Summary: Quantum mechanics in 1D.
Home-page: https://compphys.solanpaa.fi
Author: Janne Solanpää
Author-email: janne+compphys@solanpaa.fi
License: Boost Software License 1.0
Keywords: numerics linear algebra schrödinger quantum
Platform: UNKNOWN
Classifier: License :: OSI Approved :: Boost Software License 1.0 (BSL-1.0)
Classifier: Programming Language :: Python :: 3 :: Only
Classifier: Topic :: Scientific/Engineering :: Physics
Requires-Python: >=3.5
Requires-Dist: numpy
Requires-Dist: scipy
Requires-Dist: matplotlib
Requires-Dist: h5py
Requires-Dist: progressbar2
